atlas_consortia_jobq/__init__.py
atlas_consortia_jobq/queue.py
atlas_consortia_jobq-0.1.0.dist-info/licenses/LICENSE
atlas_consortia_jobq-0.1.0.dist-info/METADATA
atlas_consortia_jobq-0.1.0.dist-info/WHEEL
atlas_consortia_jobq-0.1.0.dist-info/top_level.txt
atlas_consortia_jobq-0.1.0.dist-info/RECORD
