Metadata-Version: 2.4
Name: atlas-consortia-jobq
Version: 0.1.0
Summary: Package to facilitate queueing of jobs using Redis
Author-email: Atlas Consortia <api-developers@hubmapconsortium.org>
License: MIT
Keywords: queue,JobQ,HuBMAP,Atlas Consortia JobQ
Classifier: Programming Language :: Python :: 3
Classifier: License :: OSI Approved :: MIT License
Classifier: Operating System :: OS Independent
Requires-Python: >=3.13
License-File: LICENSE
Requires-Dist: redis>=7.1.0
Dynamic: license-file
